<?xml version="1.0" encoding="UTF-8"?>
<beans xmlns="http://www.springframework.org/schema/beans"
       xmlns:xsi="http://www.w3.org/2001/XMLSchema-instance"
       xsi:schemaLocation="http://www.springframework.org/schema/beans http://www.springframework.org/schema/beans/spring-beans-3.1.xsd">

<bean id="accountings" class="be.dafke.Accounting.Objects.Accountings" scope="singleton" init-method="fromXML"/>

<bean id="accountingMainPanel" class="be.dafke.Accounting.AccountingGUIFrame" scope="singleton">
	<constructor-arg>
		<value>Boekhouding</value>
	</constructor-arg>
	<constructor-arg ref="accountings"/>
<!--<constructor-arg ref="menubar"/> -->
</bean>

<!-- Menu Bar -->
<!--
<bean id="menubar" class="be.dafke.Accounting.AccountingMenuBar" scope="singleton" init-method="activateButtons">
	<constructor-arg ref="accountings"/>
</bean>
-->

</beans>